vd/__init__.py
vd/crude.py
vd/dog.py
vd/wip/__init__.py
vd/wip/input_sourcing.py
vd/wip/input_wire.py
vd-0.0.11.dist-info/LICENSE
vd-0.0.11.dist-info/METADATA
vd-0.0.11.dist-info/WHEEL
vd-0.0.11.dist-info/top_level.txt
vd-0.0.11.dist-info/RECORD
