Metadata-Version: 2.1
Name: vd
Version: 0.0.11
Summary: Value Dispatch: Wire Python functions to stores for seamless input/output handling.
Home-page: https://github.com/i2mint/vd
License: mit
Platform: any
License-File: LICENSE
Requires-Dist: dol
Requires-Dist: i2
Requires-Dist: au
Provides-Extra: test
Requires-Dist: pytest; extra == "test"
Requires-Dist: pytest-asyncio; extra == "test"
